<?xml version="1.0" encoding="UTF-8"?><Db flnm="proyecto_porcicola" nm="proyecto_porcicola" ver="1.3.4">
  <VerLbl/>
  <VerNotes/>
  <DefTblOpts/>
  <DocFolder>/home/vicky/Documentos</DocFolder>
  <Sch Cm="" nm="public">
    <Tbl UsSo="1" nm="animal">
      <TblOpts>WITHOUT OIDS</TblOpts>
      <Pk ClNs="id" nm="pkanimal"/>
      <Cl au="1" df="nextval('animal_id_seq'::regclass)" nm="id" nu="0">
        <DT arr="0" ds="Integer" en="" id="4" ln="null" sc="null" sg="1" un="0"/>
      </Cl>
      <Cl au="0" df="" nm="peso_animal" nu="0">
        <DT arr="0" ds="VarChar" en="" id="12" ln="4" sc="null" sg="1" un="0"/>
      </Cl>
      <Cl au="0" df="" nm="edad_animal" nu="0">
        <DT arr="0" ds="Integer" en="" id="4" ln="null" sc="null" sg="1" un="0"/>
      </Cl>
      <Cl au="0" df="" nm="fecha_ingreso" nu="0">
        <DT arr="0" ds="TimeStamp" en="" id="93" ln="null" sc="null" sg="1" un="0"/>
      </Cl>
      <Cl au="0" df="" nm="precio_animal" nu="0">
        <DT arr="0" ds="Double" en="" id="8" ln="null" sc="null" sg="1" un="0"/>
      </Cl>
      <Cl au="0" df="" nm="Genero_Id" nu="0">
        <DT arr="0" ds="Integer" en="" id="4" ln="null" sc="null" sg="1" un="0"/>
      </Cl>
      <Cl au="0" df="" nm="lote_id" nu="0">
        <DT arr="0" ds="Integer" en="" id="4" ln="null" sc="null" sg="1" un="0"/>
      </Cl>
      <Cl au="0" df="" nm="raza_id" nu="1">
        <DT arr="0" ds="Integer" en="" id="4" ln="null" sc="null" sg="1" un="0"/>
      </Cl>
      <Fk deAc="3" nm="fk_animal_raza" prLkCl="id" upAc="3">
        <PrTb mn="0" nm="raza" oe="1" sch="public" zr="0"/>
        <CdTb mn="1" nm="animal" oe="0" sch="public" zr="1"/>
        <ClPr cdCl="raza_id" prCl="id"/>
      </Fk>
      <Fk deAc="3" nm="fk_Genero" prLkCl="Id" upAc="3">
        <PrTb mn="0" nm="Genero" oe="1" sch="public" zr="0"/>
        <CdTb mn="1" nm="animal" oe="0" sch="public" zr="1"/>
        <ClPr cdCl="Genero_Id" prCl="Id"/>
      </Fk>
      <Fk deAc="3" nm="fk_Lote" prLkCl="Id" upAc="3">
        <PrTb mn="0" nm="Lote" oe="1" sch="public" zr="0"/>
        <CdTb mn="1" nm="animal" oe="0" sch="public" zr="1"/>
        <ClPr cdCl="lote_id" prCl="Id"/>
      </Fk>
      <UniqueConstraints/>
      <SchTrHis/>
    </Tbl>
    <Tbl UsSo="1" nm="bitacora">
      <TblOpts>WITHOUT OIDS</TblOpts>
      <Pk ClNs="id" nm="pkbitacora"/>
      <Cl au="1" df="nextval('&quot;bitacora_Id_seq&quot;'::regclass)" nm="id" nu="0">
        <DT arr="0" ds="BigInt" en="" id="-5" ln="null" sc="null" sg="1" un="0"/>
      </Cl>
      <Cl au="0" df="" nm="fecha" nu="0">
        <DT arr="0" ds="TimeStamp" en="" id="93" ln="null" sc="null" sg="1" un="0"/>
      </Cl>
      <Cl au="0" df="" nm="accion" nu="0">
        <DT arr="0" ds="VarChar" en="" id="12" ln="80" sc="null" sg="1" un="0"/>
      </Cl>
      <Cl au="0" df="" nm="tabla" nu="0">
        <DT arr="0" ds="VarChar" en="" id="12" ln="80" sc="null" sg="1" un="0"/>
      </Cl>
      <Cl au="0" df="" nm="registro" nu="1">
        <DT arr="0" ds="BigInt" en="" id="-5" ln="null" sc="null" sg="1" un="0"/>
      </Cl>
      <Cl au="0" df="" nm="observacion" nu="1">
        <DT arr="0" ds="VarChar" en="" id="12" ln="1024" sc="null" sg="1" un="0"/>
      </Cl>
      <Cl au="0" df="" nm="usuario_id" nu="0">
        <DT arr="0" ds="Integer" en="" id="4" ln="null" sc="null" sg="1" un="0"/>
      </Cl>
      <Fk deAc="3" nm="fk_bitacora_usuario" prLkCl="id" upAc="3">
        <PrTb mn="0" nm="usuario" oe="1" sch="public" zr="0"/>
        <CdTb mn="1" nm="bitacora" oe="0" sch="public" zr="1"/>
        <ClPr cdCl="usuario_id" prCl="id"/>
      </Fk>
      <Idx clu="0" ftx="0" nm="bitacora_fecha_Idx" spa="0" unq="0">
        <ClNs>fecha</ClNs>
        <OptTx>USING btree</OptTx>
      </Idx>
      <Idx clu="0" ftx="0" nm="bitacora_usuario_Id_Idx" spa="0" unq="0">
        <ClNs>usuario_id</ClNs>
        <OptTx>USING btree</OptTx>
      </Idx>
      <UniqueConstraints/>
      <SchTrHis/>
    </Tbl>
    <Tbl UsSo="1" nm="ciudad">
      <TblOpts>WITHOUT OIDS</TblOpts>
      <Pk ClNs="id" nm="pkCiudad"/>
      <Cl au="1" df="nextval('&quot;Ciudad_Id_seq&quot;'::regclass)" nm="id" nu="0">
        <DT arr="0" ds="Integer" en="" id="4" ln="null" sc="null" sg="1" un="0"/>
      </Cl>
      <Cl au="0" df="" nm="nombre_ciudad" nu="0">
        <DT arr="0" ds="VarChar" en="" id="12" ln="50" sc="null" sg="1" un="0"/>
      </Cl>
      <Cl au="0" df="" nm="departamento_id" nu="0">
        <DT arr="0" ds="Integer" en="" id="4" ln="null" sc="null" sg="1" un="0"/>
      </Cl>
      <Cl au="0" df="" nm="deleted_at" nu="1">
        <DT arr="0" ds="TimeStamp" en="" id="93" ln="null" sc="null" sg="1" un="0"/>
      </Cl>
      <Fk deAc="3" nm="fk_Departamento" prLkCl="departamento_id" upAc="3">
        <PrTb mn="0" nm="departamento" oe="1" sch="public" zr="1"/>
        <CdTb mn="1" nm="ciudad" oe="0" sch="public" zr="1"/>
        <ClPr cdCl="departamento_id" prCl="departamento_id"/>
      </Fk>
      <UniqueConstraints/>
      <SchTrHis/>
    </Tbl>
    <Tbl UsSo="1" nm="compra_insumo">
      <TblOpts>WITHOUT OIDS</TblOpts>
      <Pk ClNs="Id" nm="pkcompra_insumo"/>
      <Cl au="1" df="nextval('&quot;compra_insumo_Id_seq&quot;'::regclass)" nm="Id" nu="0">
        <DT arr="0" ds="Integer" en="" id="4" ln="null" sc="null" sg="1" un="0"/>
      </Cl>
      <Cl au="0" df="" nm="fecha_compra" nu="0">
        <DT arr="0" ds="TimeStamp" en="" id="93" ln="null" sc="null" sg="1" un="0"/>
      </Cl>
      <Cl au="0" df="" nm="usuario_Id" nu="0">
        <DT arr="0" ds="Integer" en="" id="4" ln="null" sc="null" sg="1" un="0"/>
      </Cl>
      <UniqueConstraints/>
      <SchTrHis/>
    </Tbl>
    <Tbl UsSo="1" nm="credencial">
      <TblOpts>WITHOUT OIDS</TblOpts>
      <Pk ClNs="id" nm="pkcredencial"/>
      <Cl au="1" df="nextval('credencial_id_seq'::regclass)" nm="id" nu="0">
        <DT arr="0" ds="BigInt" en="" id="-5" ln="null" sc="null" sg="1" un="0"/>
      </Cl>
      <Cl au="0" df="now()" nm="created_at" nu="0">
        <DT arr="0" ds="TimeStamp" en="" id="93" ln="null" sc="null" sg="1" un="0"/>
      </Cl>
      <Cl au="0" df="now()" nm="updated_at" nu="0">
        <DT arr="0" ds="TimeStamp" en="" id="93" ln="null" sc="null" sg="1" un="0"/>
      </Cl>
      <Cl au="0" df="" nm="deleted_at" nu="1">
        <DT arr="0" ds="TimeStamp" en="" id="93" ln="null" sc="null" sg="1" un="0"/>
      </Cl>
      <Cl au="0" df="" nm="nombre" nu="0">
        <DT arr="0" ds="VarChar" en="" id="12" ln="50" sc="null" sg="1" un="0"/>
      </Cl>
      <UniqueConstraints/>
      <SchTrHis/>
    </Tbl>
    <Tbl UsSo="1" nm="datos_usuario">
      <TblOpts>WITHOUT OIDS</TblOpts>
      <Pk ClNs="id" nm="pkdatos_usuario"/>
      <Cl au="1" df="nextval('&quot;datos_usuario_Id_seq&quot;'::regclass)" nm="id" nu="0">
        <DT arr="0" ds="Integer" en="" id="4" ln="null" sc="null" sg="1" un="0"/>
      </Cl>
      <Cl au="0" df="now()" nm="created_at" nu="0">
        <DT arr="0" ds="TimeStamp" en="" id="93" ln="null" sc="null" sg="1" un="0"/>
      </Cl>
      <Cl au="0" df="now()" nm="updated_at" nu="0">
        <DT arr="0" ds="TimeStamp" en="" id="93" ln="null" sc="null" sg="1" un="0"/>
      </Cl>
      <Cl au="0" df="" nm="deleted_at" nu="1">
        <DT arr="0" ds="TimeStamp" en="" id="93" ln="null" sc="null" sg="1" un="0"/>
      </Cl>
      <Cl au="0" df="" nm="apellidos" nu="0">
        <DT arr="0" ds="VarChar" en="" id="12" ln="50" sc="null" sg="1" un="0"/>
      </Cl>
      <Cl au="0" df="" nm="telefono" nu="0">
        <DT arr="0" ds="VarChar" en="" id="12" ln="11" sc="null" sg="1" un="0"/>
      </Cl>
      <Cl au="0" df="" nm="direccion" nu="1">
        <DT arr="0" ds="VarChar" en="" id="12" ln="30" sc="null" sg="1" un="0"/>
      </Cl>
      <Cl au="0" df="" nm="nombre" nu="0">
        <DT arr="0" ds="VarChar" en="" id="12" ln="20" sc="null" sg="1" un="0"/>
      </Cl>
      <Cl au="0" df="" nm="cedula" nu="0">
        <DT arr="0" ds="VarChar" en="" id="12" ln="11" sc="null" sg="1" un="0"/>
      </Cl>
      <Cl au="0" df="" nm="usuario_id" nu="0">
        <DT arr="0" ds="Integer" en="" id="4" ln="null" sc="null" sg="1" un="0"/>
      </Cl>
      <Cl au="0" df="" nm="ciudad_id" nu="1">
        <DT arr="0" ds="Integer" en="" id="4" ln="null" sc="null" sg="1" un="0"/>
      </Cl>
      <Fk deAc="3" nm="fk_datos_usuario_Ciudad" prLkCl="id" upAc="3">
        <PrTb mn="0" nm="ciudad" oe="1" sch="public" zr="1"/>
        <CdTb mn="1" nm="datos_usuario" oe="0" sch="public" zr="1"/>
        <ClPr cdCl="ciudad_id" prCl="id"/>
      </Fk>
      <Fk deAc="3" nm="fk_datos_usuario_usuario" prLkCl="id" upAc="3">
        <PrTb mn="0" nm="usuario" oe="1" sch="public" zr="0"/>
        <CdTb mn="1" nm="datos_usuario" oe="0" sch="public" zr="1"/>
        <ClPr cdCl="usuario_id" prCl="id"/>
      </Fk>
      <UniqueConstraints/>
      <SchTrHis/>
    </Tbl>
    <Tbl UsSo="1" nm="departamento">
      <TblOpts>WITHOUT OIDS</TblOpts>
      <Pk ClNs="departamento_id" nm="pkDepartamento"/>
      <Cl au="1" df="nextval('&quot;Departamento_Id_seq&quot;'::regclass)" nm="departamento_id" nu="0">
        <DT arr="0" ds="Integer" en="" id="4" ln="null" sc="null" sg="1" un="0"/>
      </Cl>
      <Cl au="0" df="" nm="nombre" nu="0">
        <DT arr="0" ds="VarChar" en="" id="12" ln="50" sc="null" sg="1" un="0"/>
      </Cl>
      <UniqueConstraints/>
      <SchTrHis/>
    </Tbl>
    <Tbl UsSo="1" nm="detalle_compra_insumo">
      <TblOpts>WITHOUT OIDS</TblOpts>
      <Pk ClNs="Id, Insumo_Id" nm="pkdetalle_compra_insumo"/>
      <Cl au="1" df="nextval('&quot;detalle_compra_insumo_Id_seq&quot;'::regclass)" nm="Id" nu="0">
        <DT arr="0" ds="Integer" en="" id="4" ln="null" sc="null" sg="1" un="0"/>
      </Cl>
      <Cl au="0" df="" nm="cantidad_insumo" nu="0">
        <DT arr="0" ds="BigInt" en="" id="-5" ln="null" sc="null" sg="1" un="0"/>
      </Cl>
      <Cl au="0" df="" nm="Insumo_Id" nu="0">
        <DT arr="0" ds="Integer" en="" id="4" ln="null" sc="null" sg="1" un="0"/>
      </Cl>
      <Cl au="0" df="" nm="valor_uni" nu="0">
        <DT arr="0" ds="Double" en="" id="8" ln="null" sc="null" sg="1" un="0"/>
      </Cl>
      <Cl au="0" df="" nm="id_compraInsumo" nu="0">
        <DT arr="0" ds="Integer" en="" id="4" ln="null" sc="null" sg="1" un="0"/>
      </Cl>
      <Cl au="0" df="" nm="subtotal" nu="1">
        <DT arr="0" ds="Double" en="" id="8" ln="null" sc="null" sg="1" un="0"/>
      </Cl>
      <Cl au="0" df="" nm="compra_insumo_Id" nu="0">
        <DT arr="0" ds="Integer" en="" id="4" ln="null" sc="null" sg="1" un="0"/>
      </Cl>
      <Fk deAc="3" nm="fk_detalle_compra_insumo_compra_insumo" prLkCl="Id" upAc="3">
        <PrTb mn="0" nm="compra_insumo" oe="1" sch="public" zr="0"/>
        <CdTb mn="1" nm="detalle_compra_insumo" oe="0" sch="public" zr="1"/>
        <ClPr cdCl="compra_insumo_Id" prCl="Id"/>
      </Fk>
      <Fk deAc="3" nm="fk_detalle_compra_insumo_insumo" prLkCl="Id" upAc="3">
        <PrTb mn="0" nm="insumo" oe="1" sch="public" zr="0"/>
        <CdTb mn="1" nm="detalle_compra_insumo" oe="0" sch="public" zr="1"/>
        <ClPr cdCl="Insumo_Id" prCl="Id"/>
      </Fk>
      <Fk deAc="3" nm="fk_Insumo" prLkCl="Id" upAc="3">
        <PrTb mn="0" nm="insumo" oe="1" sch="public" zr="0"/>
        <CdTb mn="1" nm="detalle_compra_insumo" oe="0" sch="public" zr="1"/>
        <ClPr cdCl="Insumo_Id" prCl="Id"/>
      </Fk>
      <UniqueConstraints/>
      <SchTrHis/>
    </Tbl>
    <Tbl UsSo="1" nm="detalle_entrada_bodega">
      <TblOpts>WITHOUT OIDS</TblOpts>
      <Pk ClNs="id" nm="pkdetalle_entrada_bodega"/>
      <Cl au="1" df="nextval('detalle_entrada_bodega_id_seq'::regclass)" nm="id" nu="0">
        <DT arr="0" ds="Integer" en="" id="4" ln="null" sc="null" sg="1" un="0"/>
      </Cl>
      <Cl au="0" df="" nm="id_entrada" nu="1">
        <DT arr="0" ds="Integer" en="" id="4" ln="null" sc="null" sg="1" un="0"/>
      </Cl>
      <Cl au="0" df="" nm="id_tipo_insumo" nu="1">
        <DT arr="0" ds="Integer" en="" id="4" ln="null" sc="null" sg="1" un="0"/>
      </Cl>
      <Cl au="0" df="" nm="id_insumo" nu="1">
        <DT arr="0" ds="Integer" en="" id="4" ln="null" sc="null" sg="1" un="0"/>
      </Cl>
      <Cl au="0" df="" nm="descripcion" nu="1">
        <DT arr="0" ds="Char" en="" id="1" ln="1" sc="null" sg="1" un="0"/>
      </Cl>
      <Cl au="0" df="" nm="cantidad" nu="1">
        <DT arr="0" ds="Integer" en="" id="4" ln="null" sc="null" sg="1" un="0"/>
      </Cl>
      <Cl au="0" df="" nm="valor_uni" nu="1">
        <DT arr="0" ds="Double" en="" id="8" ln="null" sc="null" sg="1" un="0"/>
      </Cl>
      <Cl au="0" df="" nm="subtotal" nu="1">
        <DT arr="0" ds="Double" en="" id="8" ln="null" sc="null" sg="1" un="0"/>
      </Cl>
      <UniqueConstraints/>
      <SchTrHis/>
    </Tbl>
    <Tbl UsSo="1" nm="detalle_proceso_venta">
      <TblOpts>WITHOUT OIDS</TblOpts>
      <Pk ClNs="Id" nm="pkdetalle_proceso_venta"/>
      <Cl au="1" df="nextval('&quot;detalle_proceso_venta_Id_seq&quot;'::regclass)" nm="Id" nu="0">
        <DT arr="0" ds="Integer" en="" id="4" ln="null" sc="null" sg="1" un="0"/>
      </Cl>
      <Cl au="0" df="" nm="peso_Animal" nu="0">
        <DT arr="0" ds="Integer" en="" id="4" ln="null" sc="null" sg="1" un="0"/>
      </Cl>
      <Cl au="0" df="" nm="precio_animal" nu="0">
        <DT arr="0" ds="Double" en="" id="8" ln="null" sc="null" sg="1" un="0"/>
      </Cl>
      <Cl au="0" df="" nm="animal_Id" nu="0">
        <DT arr="0" ds="Integer" en="" id="4" ln="null" sc="null" sg="1" un="0"/>
      </Cl>
      <Cl au="0" df="" nm="id_venta" nu="1">
        <DT arr="0" ds="Double" en="" id="8" ln="null" sc="null" sg="1" un="0"/>
      </Cl>
      <UniqueConstraints/>
      <SchTrHis/>
    </Tbl>
    <Tbl UsSo="1" nm="detalle_salida_bodega">
      <TblOpts>WITHOUT OIDS</TblOpts>
      <Pk ClNs="id" nm="pkdetalle_salida_bodega"/>
      <Cl au="1" df="nextval('detalle_salida_bodega_id_seq'::regclass)" nm="id" nu="0">
        <DT arr="0" ds="Integer" en="" id="4" ln="null" sc="null" sg="1" un="0"/>
      </Cl>
      <Cl au="0" df="" nm="id_salida" nu="1">
        <DT arr="0" ds="Integer" en="" id="4" ln="null" sc="null" sg="1" un="0"/>
      </Cl>
      <Cl au="0" df="" nm="id_tipo_insumo" nu="1">
        <DT arr="0" ds="Integer" en="" id="4" ln="null" sc="null" sg="1" un="0"/>
      </Cl>
      <Cl au="0" df="" nm="id_insumo" nu="1">
        <DT arr="0" ds="Integer" en="" id="4" ln="null" sc="null" sg="1" un="0"/>
      </Cl>
      <Cl au="0" df="" nm="descripcion" nu="1">
        <DT arr="0" ds="Char" en="" id="1" ln="100" sc="null" sg="1" un="0"/>
      </Cl>
      <Cl au="0" df="" nm="cantidad" nu="1">
        <DT arr="0" ds="Integer" en="" id="4" ln="null" sc="null" sg="1" un="0"/>
      </Cl>
      <Cl au="0" df="" nm="valor_uni" nu="1">
        <DT arr="0" ds="Double" en="" id="8" ln="null" sc="null" sg="1" un="0"/>
      </Cl>
      <Cl au="0" df="" nm="subtotal" nu="1">
        <DT arr="0" ds="Double" en="" id="8" ln="null" sc="null" sg="1" un="0"/>
      </Cl>
      <UniqueConstraints/>
      <SchTrHis/>
    </Tbl>
    <Tbl UsSo="1" nm="entrada_bodega">
      <TblOpts>WITHOUT OIDS</TblOpts>
      <Cl au="0" df="" nm="id" nu="0">
        <DT arr="0" ds="Integer" en="" id="4" ln="null" sc="null" sg="1" un="0"/>
      </Cl>
      <Cl au="0" df="" nm="id_usuario" nu="1">
        <DT arr="0" ds="Integer" en="" id="4" ln="null" sc="null" sg="1" un="0"/>
      </Cl>
      <Cl au="0" df="" nm="fecha" nu="1">
        <DT arr="0" ds="Date" en="" id="91" ln="null" sc="null" sg="1" un="0"/>
      </Cl>
      <Fk deAc="3" nm="fk_entrada_bodega_usuario" prLkCl="id" upAc="3">
        <PrTb mn="0" nm="usuario" oe="1" sch="public" zr="0"/>
        <CdTb mn="1" nm="entrada_bodega" oe="0" sch="public" zr="1"/>
        <ClPr cdCl="id" prCl="id"/>
      </Fk>
      <UniqueConstraints/>
      <SchTrHis/>
    </Tbl>
    <Tbl UsSo="1" nm="Genero">
      <TblOpts>WITHOUT OIDS</TblOpts>
      <Pk ClNs="Id" nm="pkGenero"/>
      <Cl au="1" df="nextval('&quot;Genero_Id_seq&quot;'::regclass)" nm="Id" nu="0">
        <DT arr="0" ds="Integer" en="" id="4" ln="null" sc="null" sg="1" un="0"/>
      </Cl>
      <Cl au="0" df="" nm="nombre_genero" nu="0">
        <DT arr="0" ds="VarChar" en="" id="12" ln="50" sc="null" sg="1" un="0"/>
      </Cl>
      <Cl au="0" df="" nm="deleted_at" nu="1">
        <DT arr="0" ds="TimeStamp" en="" id="93" ln="null" sc="null" sg="1" un="0"/>
      </Cl>
      <UniqueConstraints/>
      <SchTrHis/>
    </Tbl>
    <Tbl UsSo="1" nm="gestacion">
      <TblOpts>WITHOUT OIDS</TblOpts>
      <Pk ClNs="id" nm="pkgestacion"/>
      <Cl au="1" df="nextval('gestacion_id_seq'::regclass)" nm="id" nu="0">
        <DT arr="0" ds="Integer" en="" id="4" ln="null" sc="null" sg="1" un="0"/>
      </Cl>
      <Cl au="0" df="" nm="fecha" nu="0">
        <DT arr="0" ds="Date" en="" id="91" ln="null" sc="null" sg="1" un="0"/>
      </Cl>
      <Cl au="0" df="" nm="fecha_monta" nu="0">
        <DT arr="0" ds="Date" en="" id="91" ln="null" sc="null" sg="1" un="0"/>
      </Cl>
      <Cl au="0" df="" nm="animal_id" nu="0">
        <DT arr="0" ds="Integer" en="" id="4" ln="null" sc="null" sg="1" un="0"/>
      </Cl>
      <Cl au="0" df="" nm="usuario_id" nu="0">
        <DT arr="0" ds="BigInt" en="" id="-5" ln="null" sc="null" sg="1" un="0"/>
      </Cl>
      <Cl au="0" df="" nm="raza_id" nu="0">
        <DT arr="0" ds="Integer" en="" id="4" ln="null" sc="null" sg="1" un="0"/>
      </Cl>
      <Fk deAc="3" nm="fk_gestacion_animal" prLkCl="id" upAc="3">
        <PrTb mn="0" nm="animal" oe="1" sch="public" zr="0"/>
        <CdTb mn="1" nm="gestacion" oe="0" sch="public" zr="1"/>
        <ClPr cdCl="animal_id" prCl="id"/>
      </Fk>
      <Fk deAc="3" nm="fk_gestacion_raza" prLkCl="id" upAc="3">
        <PrTb mn="0" nm="raza" oe="1" sch="public" zr="0"/>
        <CdTb mn="1" nm="gestacion" oe="0" sch="public" zr="1"/>
        <ClPr cdCl="raza_id" prCl="id"/>
      </Fk>
      <Fk deAc="3" nm="fk_gestacion_usuario" prLkCl="id" upAc="3">
        <PrTb mn="0" nm="usuario" oe="1" sch="public" zr="0"/>
        <CdTb mn="1" nm="gestacion" oe="0" sch="public" zr="1"/>
        <ClPr cdCl="usuario_id" prCl="id"/>
      </Fk>
      <UniqueConstraints/>
      <SchTrHis/>
    </Tbl>
    <Tbl UsSo="1" nm="insumo">
      <TblOpts>WITHOUT OIDS</TblOpts>
      <Pk ClNs="Id" nm="pkInsumo"/>
      <Cl au="1" df="nextval('&quot;Insumo_Id_seq&quot;'::regclass)" nm="Id" nu="0">
        <DT arr="0" ds="Integer" en="" id="4" ln="null" sc="null" sg="1" un="0"/>
      </Cl>
      <Cl au="0" df="" nm="nombreInsumo" nu="0">
        <DT arr="0" ds="VarChar" en="" id="12" ln="50" sc="null" sg="1" un="0"/>
      </Cl>
      <Cl au="0" df="" nm="fecha_fab" nu="1">
        <DT arr="0" ds="Date" en="" id="91" ln="null" sc="null" sg="1" un="0"/>
      </Cl>
      <Cl au="0" df="" nm="fecha_ven" nu="1">
        <DT arr="0" ds="Date" en="" id="91" ln="null" sc="null" sg="1" un="0"/>
      </Cl>
      <Cl au="0" df="" nm="tipo_insumo_id" nu="0">
        <DT arr="0" ds="Integer" en="" id="4" ln="null" sc="null" sg="1" un="0"/>
      </Cl>
      <Fk deAc="3" nm="fk_insumo_tipo_insumo" prLkCl="id" upAc="3">
        <PrTb mn="0" nm="tipo_insumo" oe="1" sch="public" zr="0"/>
        <CdTb mn="1" nm="insumo" oe="0" sch="public" zr="1"/>
        <ClPr cdCl="tipo_insumo_id" prCl="id"/>
      </Fk>
      <UniqueConstraints/>
      <SchTrHis/>
    </Tbl>
    <Tbl UsSo="1" nm="Lote">
      <TblOpts>WITHOUT OIDS</TblOpts>
      <Pk ClNs="Id" nm="pkLote"/>
      <Cl au="1" df="nextval('&quot;Lote_Id_seq&quot;'::regclass)" nm="Id" nu="0">
        <DT arr="0" ds="Integer" en="" id="4" ln="null" sc="null" sg="1" un="0"/>
      </Cl>
      <Cl au="0" df="" nm="nombreLote" nu="0">
        <DT arr="0" ds="VarChar" en="" id="12" ln="50" sc="null" sg="1" un="0"/>
      </Cl>
      <Cl au="0" df="" nm="deleted_at" nu="1">
        <DT arr="0" ds="TimeStamp" en="" id="93" ln="null" sc="null" sg="1" un="0"/>
      </Cl>
      <UniqueConstraints/>
      <SchTrHis/>
    </Tbl>
    <Tbl UsSo="1" nm="proceso_venta">
      <TblOpts>WITHOUT OIDS</TblOpts>
      <Pk ClNs="Id" nm="pkproceso_venta"/>
      <Cl au="1" df="nextval('&quot;proceso_venta_Id_seq&quot;'::regclass)" nm="Id" nu="0">
        <DT arr="0" ds="Integer" en="" id="4" ln="null" sc="null" sg="1" un="0"/>
      </Cl>
      <Cl au="0" df="" nm="fecha_hora_venta" nu="0">
        <DT arr="0" ds="TimeStamp" en="" id="93" ln="null" sc="null" sg="1" un="0"/>
      </Cl>
      <Cl au="0" df="" nm="usuario_id" nu="1">
        <DT arr="0" ds="BigInt" en="" id="-5" ln="null" sc="null" sg="1" un="0"/>
      </Cl>
      <Fk deAc="3" nm="fk_proceso_venta_usuario" prLkCl="id" upAc="3">
        <PrTb mn="0" nm="usuario" oe="1" sch="public" zr="0"/>
        <CdTb mn="1" nm="proceso_venta" oe="0" sch="public" zr="1"/>
        <ClPr cdCl="usuario_id" prCl="id"/>
      </Fk>
      <UniqueConstraints/>
      <SchTrHis/>
    </Tbl>
    <Tbl UsSo="1" nm="raza">
      <TblOpts>WITHOUT OIDS</TblOpts>
      <Pk ClNs="id" nm="pkRaza"/>
      <Cl au="1" df="nextval('&quot;Raza_Id_seq&quot;'::regclass)" nm="id" nu="0">
        <DT arr="0" ds="Integer" en="" id="4" ln="null" sc="null" sg="1" un="0"/>
      </Cl>
      <Cl au="0" df="" nm="nombre_raza" nu="0">
        <DT arr="0" ds="VarChar" en="" id="12" ln="50" sc="null" sg="1" un="0"/>
      </Cl>
      <Cl au="0" df="" nm="deleted_at" nu="1">
        <DT arr="0" ds="TimeStamp" en="" id="93" ln="null" sc="null" sg="1" un="0"/>
      </Cl>
      <UniqueConstraints/>
      <SchTrHis/>
    </Tbl>
    <Tbl UsSo="1" nm="recordar_me">
      <TblOpts>WITHOUT OIDS</TblOpts>
      <Pk ClNs="id" nm="pkrecordar_me"/>
      <Cl au="1" df="nextval('recordar_me_id_seq'::regclass)" nm="id" nu="0">
        <DT arr="0" ds="Integer" en="" id="4" ln="null" sc="null" sg="1" un="0"/>
      </Cl>
      <Cl au="0" df="" nm="ip_addres" nu="0">
        <DT arr="0" ds="VarChar" en="" id="12" ln="50" sc="null" sg="1" un="0"/>
      </Cl>
      <Cl au="0" df="" nm="hash_cookie" nu="0">
        <DT arr="0" ds="VarChar" en="" id="12" ln="32" sc="null" sg="1" un="0"/>
      </Cl>
      <Cl au="0" df="" nm="created_at" nu="0">
        <DT arr="0" ds="VarChar" en="" id="12" ln="32" sc="null" sg="1" un="0"/>
      </Cl>
      <Cl au="0" df="" nm="usuario_Id" nu="0">
        <DT arr="0" ds="Integer" en="" id="4" ln="null" sc="null" sg="1" un="0"/>
      </Cl>
      <Fk deAc="3" nm="fk_recordar_me_usuario" prLkCl="id" upAc="3">
        <PrTb mn="0" nm="usuario" oe="1" sch="public" zr="1"/>
        <CdTb mn="1" nm="recordar_me" oe="0" sch="public" zr="1"/>
        <ClPr cdCl="usuario_Id" prCl="id"/>
      </Fk>
      <Idx clu="0" ftx="0" nm="recordar_me_hash_cookie_Idx" spa="0" unq="0">
        <ClNs>hash_cookie</ClNs>
        <OptTx>USING btree</OptTx>
      </Idx>
      <Idx clu="0" ftx="0" nm="recordar_me_ip_addres_Idx" spa="0" unq="0">
        <ClNs>ip_addres</ClNs>
        <OptTx>USING btree</OptTx>
      </Idx>
      <UniqueConstraints/>
      <SchTrHis/>
    </Tbl>
    <Tbl UsSo="1" nm="registro_parto">
      <TblOpts>WITHOUT OIDS</TblOpts>
      <Pk ClNs="Id" nm="pkregistro_parto"/>
      <Cl au="1" df="nextval('&quot;registro_parto_Id_seq&quot;'::regclass)" nm="Id" nu="0">
        <DT arr="0" ds="Integer" en="" id="4" ln="null" sc="null" sg="1" un="0"/>
      </Cl>
      <Cl au="0" df="" nm="fecha_nacimiento" nu="0">
        <DT arr="0" ds="Date" en="" id="91" ln="null" sc="null" sg="1" un="0"/>
      </Cl>
      <Cl au="0" df="0" nm="hembras_nacidas_vivas" nu="0">
        <DT arr="0" ds="Integer" en="" id="4" ln="null" sc="null" sg="1" un="0"/>
      </Cl>
      <Cl au="0" df="0" nm="machos_nacidos_vivos" nu="1">
        <DT arr="0" ds="Integer" en="" id="4" ln="null" sc="null" sg="1" un="0"/>
      </Cl>
      <Cl au="0" df="0" nm="nacidos_muertos" nu="1">
        <DT arr="0" ds="Integer" en="" id="4" ln="null" sc="null" sg="1" un="0"/>
      </Cl>
      <Cl au="0" df="" nm="animal_id" nu="1">
        <DT arr="0" ds="Integer" en="" id="4" ln="null" sc="null" sg="1" un="0"/>
      </Cl>
      <Cl au="0" df="" nm="raza_id" nu="1">
        <DT arr="0" ds="Integer" en="" id="4" ln="null" sc="null" sg="1" un="0"/>
      </Cl>
      <Fk deAc="3" nm="fk_registro_parto_animal" prLkCl="id" upAc="3">
        <PrTb mn="0" nm="animal" oe="1" sch="public" zr="0"/>
        <CdTb mn="1" nm="registro_parto" oe="0" sch="public" zr="1"/>
        <ClPr cdCl="animal_id" prCl="id"/>
      </Fk>
      <Fk deAc="3" nm="fk_registro_parto_raza" prLkCl="id" upAc="3">
        <PrTb mn="0" nm="raza" oe="1" sch="public" zr="0"/>
        <CdTb mn="1" nm="registro_parto" oe="0" sch="public" zr="1"/>
        <ClPr cdCl="raza_id" prCl="id"/>
      </Fk>
      <UniqueConstraints/>
      <SchTrHis/>
    </Tbl>
    <Tbl UsSo="1" nm="registro_vacunacion">
      <TblOpts>WITHOUT OIDS</TblOpts>
      <Pk ClNs="Id" nm="pkregistro_vacunacion"/>
      <Cl au="1" df="nextval('&quot;registro_vacunacion_Id_seq&quot;'::regclass)" nm="Id" nu="0">
        <DT arr="0" ds="Integer" en="" id="4" ln="null" sc="null" sg="1" un="0"/>
      </Cl>
      <Cl au="0" df="" nm="fecha_hora_vacunacion" nu="0">
        <DT arr="0" ds="TimeStamp" en="" id="93" ln="null" sc="null" sg="1" un="0"/>
      </Cl>
      <Cl au="0" df="" nm="animal_id" nu="1">
        <DT arr="0" ds="Integer" en="" id="4" ln="null" sc="null" sg="1" un="0"/>
      </Cl>
      <Cl au="0" df="" nm="usuario_id" nu="1">
        <DT arr="0" ds="BigInt" en="" id="-5" ln="null" sc="null" sg="1" un="0"/>
      </Cl>
      <Cl au="0" df="" nm="vacuna_id" nu="1">
        <DT arr="0" ds="Integer" en="" id="4" ln="null" sc="null" sg="1" un="0"/>
      </Cl>
      <Fk deAc="3" nm="fk_registro_vacunacion_animal" prLkCl="id" upAc="3">
        <PrTb mn="0" nm="animal" oe="1" sch="public" zr="0"/>
        <CdTb mn="1" nm="registro_vacunacion" oe="0" sch="public" zr="1"/>
        <ClPr cdCl="animal_id" prCl="id"/>
      </Fk>
      <Fk deAc="3" nm="fk_registro_vacunacion_usuario" prLkCl="id" upAc="3">
        <PrTb mn="0" nm="usuario" oe="1" sch="public" zr="0"/>
        <CdTb mn="1" nm="registro_vacunacion" oe="0" sch="public" zr="1"/>
        <ClPr cdCl="usuario_id" prCl="id"/>
      </Fk>
      <Fk deAc="3" nm="fk_registro_vacunacion_vacuna" prLkCl="id" upAc="3">
        <PrTb mn="0" nm="vacuna" oe="1" sch="public" zr="0"/>
        <CdTb mn="1" nm="registro_vacunacion" oe="0" sch="public" zr="1"/>
        <ClPr cdCl="vacuna_id" prCl="id"/>
      </Fk>
      <UniqueConstraints/>
      <SchTrHis/>
    </Tbl>
    <Tbl UsSo="1" nm="salida_bodega">
      <TblOpts>WITHOUT OIDS</TblOpts>
      <Pk ClNs="Id" nm="pksalida_bodega"/>
      <Cl au="1" df="nextval('&quot;salida_bodega_Id_seq&quot;'::regclass)" nm="Id" nu="0">
        <DT arr="0" ds="Integer" en="" id="4" ln="null" sc="null" sg="1" un="0"/>
      </Cl>
      <Cl au="0" df="" nm="fecha" nu="0">
        <DT arr="0" ds="Date" en="" id="91" ln="null" sc="null" sg="1" un="0"/>
      </Cl>
      <Cl au="0" df="" nm="usuario_id" nu="1">
        <DT arr="0" ds="BigInt" en="" id="-5" ln="null" sc="null" sg="1" un="0"/>
      </Cl>
      <Fk deAc="3" nm="fk_salida_bodega_usuario" prLkCl="id" upAc="3">
        <PrTb mn="0" nm="usuario" oe="1" sch="public" zr="0"/>
        <CdTb mn="1" nm="salida_bodega" oe="0" sch="public" zr="1"/>
        <ClPr cdCl="usuario_id" prCl="id"/>
      </Fk>
      <UniqueConstraints/>
      <SchTrHis/>
    </Tbl>
    <Tbl UsSo="1" nm="tipo_insumo">
      <TblOpts>WITHOUT OIDS</TblOpts>
      <Pk ClNs="id" nm="pktipo_insumo"/>
      <Cl au="1" df="nextval('tipo_insumo_id_seq'::regclass)" nm="id" nu="0">
        <DT arr="0" ds="Integer" en="" id="4" ln="null" sc="null" sg="1" un="0"/>
      </Cl>
      <Cl au="0" df="" nm="descripcion" nu="1">
        <DT arr="0" ds="VarChar" en="" id="12" ln="20" sc="null" sg="1" un="0"/>
      </Cl>
      <UniqueConstraints/>
      <SchTrHis/>
    </Tbl>
    <Tbl UsSo="1" nm="usuario">
      <TblOpts>WITHOUT OIDS</TblOpts>
      <Pk ClNs="id" nm="pkusuario"/>
      <Cl au="1" df="nextval('&quot;usuario_Id_seq&quot;'::regclass)" nm="id" nu="0">
        <DT arr="0" ds="BigInt" en="" id="-5" ln="null" sc="null" sg="1" un="0"/>
      </Cl>
      <Cl au="0" df="now()" nm="created_at" nu="0">
        <DT arr="0" ds="TimeStamp" en="" id="93" ln="null" sc="null" sg="1" un="0"/>
      </Cl>
      <Cl au="0" df="now()" nm="updated_at" nu="0">
        <DT arr="0" ds="TimeStamp" en="" id="93" ln="null" sc="null" sg="1" un="0"/>
      </Cl>
      <Cl au="0" df="" nm="deleted_at" nu="1">
        <DT arr="0" ds="TimeStamp" en="" id="93" ln="null" sc="null" sg="1" un="0"/>
      </Cl>
      <Cl au="0" df="" nm="user_name" nu="0">
        <DT arr="0" ds="VarChar" en="" id="12" ln="50" sc="null" sg="1" un="0"/>
      </Cl>
      <Cl au="0" df="" nm="password" nu="0">
        <DT arr="0" ds="VarChar" en="" id="12" ln="32" sc="null" sg="1" un="0"/>
      </Cl>
      <Cl au="0" df="true" nm="actived" nu="0">
        <DT arr="0" ds="Boolean" en="" id="16" ln="null" sc="null" sg="1" un="0"/>
      </Cl>
      <Cl au="0" df="" nm="last_login_at" nu="1">
        <DT arr="0" ds="TimeStamp" en="" id="93" ln="null" sc="null" sg="1" un="0"/>
      </Cl>
      <Idx clu="0" ftx="0" nm="usuario_deleted_at_Idx" spa="0" unq="0">
        <ClNs>deleted_at</ClNs>
        <OptTx>USING btree</OptTx>
      </Idx>
      <Idx clu="0" ftx="0" nm="usuario_password_Idx" spa="0" unq="0">
        <ClNs>password</ClNs>
        <OptTx>USING btree</OptTx>
      </Idx>
      <Idx clu="0" ftx="0" nm="usuario_user_name_Idx" spa="0" unq="0">
        <ClNs>user_name</ClNs>
        <OptTx>USING btree</OptTx>
      </Idx>
      <UniqueConstraints/>
      <SchTrHis/>
    </Tbl>
    <Tbl UsSo="1" nm="usuario_credencial">
      <TblOpts>WITHOUT OIDS</TblOpts>
      <Pk ClNs="id" nm="pkusuario_credencial"/>
      <Cl au="1" df="nextval('&quot;usuario_credencial_Id_seq&quot;'::regclass)" nm="id" nu="0">
        <DT arr="0" ds="BigInt" en="" id="-5" ln="null" sc="null" sg="1" un="0"/>
      </Cl>
      <Cl au="0" df="now()" nm="created_at" nu="0">
        <DT arr="0" ds="TimeStamp" en="" id="93" ln="null" sc="null" sg="1" un="0"/>
      </Cl>
      <Cl au="0" df="" nm="usuario_id" nu="0">
        <DT arr="0" ds="BigInt" en="" id="-5" ln="null" sc="null" sg="1" un="0"/>
      </Cl>
      <Cl au="0" df="" nm="credencial_id" nu="0">
        <DT arr="0" ds="BigInt" en="" id="-5" ln="null" sc="null" sg="1" un="0"/>
      </Cl>
      <Fk deAc="3" nm="fk_credencial" prLkCl="id" upAc="3">
        <PrTb mn="0" nm="credencial" oe="1" sch="public" zr="0"/>
        <CdTb mn="1" nm="usuario_credencial" oe="0" sch="public" zr="1"/>
        <ClPr cdCl="credencial_id" prCl="id"/>
      </Fk>
      <Fk deAc="3" nm="fk_usuario" prLkCl="id" upAc="3">
        <PrTb mn="0" nm="usuario" oe="1" sch="public" zr="0"/>
        <CdTb mn="1" nm="usuario_credencial" oe="0" sch="public" zr="1"/>
        <ClPr cdCl="usuario_id" prCl="id"/>
      </Fk>
      <Idx clu="0" ftx="0" nm="usuario_credencial_credencial_Id_Idx" spa="0" unq="0">
        <ClNs>credencial_id</ClNs>
        <OptTx>USING btree</OptTx>
      </Idx>
      <Idx clu="0" ftx="0" nm="usuario_credencial_usuario_Id_Idx" spa="0" unq="0">
        <ClNs>usuario_id</ClNs>
        <OptTx>USING btree</OptTx>
      </Idx>
      <UniqueConstraints/>
      <SchTrHis/>
    </Tbl>
    <Tbl UsSo="1" nm="vacuna">
      <TblOpts>WITHOUT OIDS</TblOpts>
      <Pk ClNs="id" nm="pkvacuna"/>
      <Cl au="1" df="nextval('&quot;Vacuna_Id_seq&quot;'::regclass)" nm="id" nu="0">
        <DT arr="0" ds="Integer" en="" id="4" ln="null" sc="null" sg="1" un="0"/>
      </Cl>
      <Cl au="0" df="" nm="nombreVacuna" nu="0">
        <DT arr="0" ds="VarChar" en="" id="12" ln="50" sc="null" sg="1" un="0"/>
      </Cl>
      <Cl au="0" df="" nm="lote_vacuna" nu="0">
        <DT arr="0" ds="Integer" en="" id="4" ln="null" sc="null" sg="1" un="0"/>
      </Cl>
      <Cl au="0" df="" nm="fehca_fabricacion_vacuna" nu="0">
        <DT arr="0" ds="Date" en="" id="91" ln="null" sc="null" sg="1" un="0"/>
      </Cl>
      <Cl au="0" df="" nm="fecha_vencimiento_Vacuna" nu="0">
        <DT arr="0" ds="Date" en="" id="91" ln="null" sc="null" sg="1" un="0"/>
      </Cl>
      <Cl au="0" df="" nm="dosis_vacuna" nu="0">
        <DT arr="0" ds="VarChar" en="" id="12" ln="20" sc="null" sg="1" un="0"/>
      </Cl>
      <UniqueConstraints/>
      <SchTrHis/>
    </Tbl>
    <Seq incr="1" nm="animal_id_seq">
      <Cm>DbWrench Autogenerated Sequence.</Cm>
    </Seq>
    <Seq incr="1" nm="bitacora_Id_seq">
      <Cm>DbWrench Autogenerated Sequence.</Cm>
    </Seq>
    <Seq incr="1" nm="Ciudad_Id_seq">
      <Cm>DbWrench Autogenerated Sequence.</Cm>
    </Seq>
    <Seq incr="1" nm="compra_insumo_Id_seq">
      <Cm>DbWrench Autogenerated Sequence.</Cm>
    </Seq>
    <Seq incr="1" nm="credencial_id_seq">
      <Cm>DbWrench Autogenerated Sequence.</Cm>
    </Seq>
    <Seq incr="1" nm="datos_usuario_Id_seq">
      <Cm>DbWrench Autogenerated Sequence.</Cm>
    </Seq>
    <Seq incr="1" nm="Departamento_Id_seq">
      <Cm>DbWrench Autogenerated Sequence.</Cm>
    </Seq>
    <Seq incr="1" nm="detalle_compra_insumo_Id_seq">
      <Cm>DbWrench Autogenerated Sequence.</Cm>
    </Seq>
    <Seq incr="1" nm="detalle_entrada_bodega_id_seq">
      <Cm>DbWrench Autogenerated Sequence.</Cm>
    </Seq>
    <Seq incr="1" nm="detalle_proceso_compra_Id_seq">
      <Cm>DbWrench Autogenerated Sequence.</Cm>
    </Seq>
    <Seq incr="1" nm="detalle_proceso_venta_Id_seq">
      <Cm>DbWrench Autogenerated Sequence.</Cm>
    </Seq>
    <Seq incr="1" nm="detalle_salida_bodega_id_seq">
      <Cm>DbWrench Autogenerated Sequence.</Cm>
    </Seq>
    <Seq incr="1" nm="Genero_Id_seq">
      <Cm>DbWrench Autogenerated Sequence.</Cm>
    </Seq>
    <Seq incr="1" nm="gestacion_id_seq">
      <Cm>DbWrench Autogenerated Sequence.</Cm>
    </Seq>
    <Seq incr="1" nm="Insumo_Id_seq">
      <Cm>DbWrench Autogenerated Sequence.</Cm>
    </Seq>
    <Seq incr="1" nm="Lote_Id_seq">
      <Cm>DbWrench Autogenerated Sequence.</Cm>
    </Seq>
    <Seq incr="1" nm="proceso_compra_Id_seq">
      <Cm>DbWrench Autogenerated Sequence.</Cm>
    </Seq>
    <Seq incr="1" nm="proceso_venta_Id_seq">
      <Cm>DbWrench Autogenerated Sequence.</Cm>
    </Seq>
    <Seq incr="1" nm="Raza_Id_seq">
      <Cm>DbWrench Autogenerated Sequence.</Cm>
    </Seq>
    <Seq incr="1" nm="recordar_me_id_seq">
      <Cm>DbWrench Autogenerated Sequence.</Cm>
    </Seq>
    <Seq incr="1" nm="registro_parto_Id_seq">
      <Cm>DbWrench Autogenerated Sequence.</Cm>
    </Seq>
    <Seq incr="1" nm="registro_vacunacion_Id_seq">
      <Cm>DbWrench Autogenerated Sequence.</Cm>
    </Seq>
    <Seq incr="1" nm="salida_bodega_Id_seq">
      <Cm>DbWrench Autogenerated Sequence.</Cm>
    </Seq>
    <Seq incr="1" nm="tipo_insumo_id_seq">
      <Cm>DbWrench Autogenerated Sequence.</Cm>
    </Seq>
    <Seq incr="1" nm="usuario_credencial_Id_seq">
      <Cm>DbWrench Autogenerated Sequence.</Cm>
    </Seq>
    <Seq incr="1" nm="usuario_Id_seq">
      <Cm>DbWrench Autogenerated Sequence.</Cm>
    </Seq>
    <Seq incr="1" nm="Vacuna_Id_seq">
      <Cm>DbWrench Autogenerated Sequence.</Cm>
    </Seq>
    <CustomTypes/>
  </Sch>
  <Sch Cm="" nm="schemaA">
    <CustomTypes/>
  </Sch>
  <Dgm nm="diagramA">
    <RnCf ClkAct="true" FtSz="11" lkStgy="RightAngleStrategy" zm="1.0">
      <VbCfg>
        <Fg ky="Auto Number" vl="0"/>
        <Fg ky="Check" vl="0"/>
        <Fg ky="Comment" vl="0"/>
        <Fg ky="Data Type" vl="1"/>
        <Fg ky="Default" vl="0"/>
        <Fg ky="ENUM Values" vl="0"/>
        <Fg ky="Length" vl="1"/>
        <Fg ky="Name" vl="1"/>
        <Fg ky="Nullable" vl="0"/>
        <Fg ky="Schema Name" vl="0"/>
        <Fg ky="Signed" vl="0"/>
      </VbCfg>
    </RnCf>
    <DiaProps>
      <Show AllCols="1" FkCols="1" FkNms="1" PkCols="1"/>
      <ErNotation>DbwErNotation</ErNotation>
      <DbTableRectangleFill>HeaderFooterFill</DbTableRectangleFill>
      <svg path=""/>
    </DiaProps>
    <TbGl bkCl="ff6666ff" sch="public" tbl="animal" x="405" y="50"/>
    <TbGl bkCl="ff6666ff" sch="public" tbl="bitacora" x="1540" y="50"/>
    <TbGl bkCl="ff6666ff" sch="public" tbl="ciudad" x="382" y="449"/>
    <TbGl bkCl="ff6666ff" sch="public" tbl="compra_insumo" x="1823" y="11"/>
    <TbGl bkCl="ff6666ff" sch="public" tbl="credencial" x="1079" y="278"/>
    <TbGl bkCl="ff6666ff" sch="public" tbl="datos_usuario" x="50" y="449"/>
    <TbGl bkCl="ff6666ff" sch="public" tbl="departamento" x="747" y="449"/>
    <TbGl bkCl="ff6666ff" sch="public" tbl="detalle_compra_insumo" x="560" y="644"/>
    <TbGl bkCl="ff6666ff" sch="public" tbl="detalle_entrada_bodega" x="2118" y="50"/>
    <TbGl bkCl="ff6666ff" sch="public" tbl="detalle_proceso_venta" x="2386" y="50"/>
    <TbGl bkCl="ff6666ff" sch="public" tbl="detalle_salida_bodega" x="1540" y="196"/>
    <TbGl bkCl="ff6666ff" sch="public" tbl="entrada_bodega" x="1302" y="440"/>
    <TbGl bkCl="ff6666ff" sch="public" tbl="Genero" x="50" y="50"/>
    <TbGl bkCl="ff6666ff" sch="public" tbl="gestacion" x="1067" y="616"/>
    <TbGl bkCl="ff6666ff" sch="public" tbl="insumo" x="50" y="659"/>
    <TbGl bkCl="ff6666ff" sch="public" tbl="Lote" x="751" y="185"/>
    <TbGl bkCl="ff6666ff" sch="public" tbl="proceso_venta" x="1245" y="186"/>
    <TbGl bkCl="ff6666ff" sch="public" tbl="raza" x="50" y="804"/>
    <TbGl bkCl="ff6666ff" sch="public" tbl="recordar_me" x="26" y="195"/>
    <TbGl bkCl="ff6666ff" sch="public" tbl="registro_parto" x="368" y="800"/>
    <TbGl bkCl="ff6666ff" sch="public" tbl="registro_vacunacion" x="744" y="67"/>
    <TbGl bkCl="ff6666ff" sch="public" tbl="salida_bodega" x="1540" y="342"/>
    <TbGl bkCl="ff6666ff" sch="public" tbl="tipo_insumo" x="53" y="927"/>
    <TbGl bkCl="ff6666ff" sch="public" tbl="usuario" x="389" y="278"/>
    <TbGl bkCl="ff6666ff" sch="public" tbl="usuario_credencial" x="739" y="278"/>
    <TbGl bkCl="ff6666ff" sch="public" tbl="vacuna" x="1149" y="50"/>
    <FkGl bkCl="ff000000" childEdge="SOUTH" nm="public.animal.fk_animal_raza" parentEdge="EAST" positioner="TwoLineUserLinkPositioner">
      <positionableLines>
        <positionableLine lineRole="PARENT_LINE" x1="296" x2="514" y1="837" y2="837"/>
        <positionableLine lineRole="CHILD_LINE" x1="518" x2="518" y1="204" y2="833"/>
      </positionableLines>
    </FkGl>
    <FkGl bkCl="ff000000" childEdge="WEST" nm="public.animal.fk_Genero" parentEdge="EAST" positioner="OneLineUserLinkPositioner">
      <positionableLines>
        <positionableLine lineRole="SINGLE_LINE" x1="312" x2="382" y1="83" y2="83"/>
      </positionableLines>
    </FkGl>
    <FkGl bkCl="ff000000" childEdge="SOUTH" nm="public.animal.fk_Lote" parentEdge="WEST" positioner="TwoLineUserLinkPositioner">
      <positionableLines>
        <positionableLine lineRole="PARENT_LINE" x1="728" x2="522" y1="211" y2="211"/>
        <positionableLine lineRole="CHILD_LINE" x1="518" x2="518" y1="204" y2="207"/>
      </positionableLines>
    </FkGl>
    <FkGl bkCl="ff000000" childEdge="SOUTH" nm="public.bitacora.fk_bitacora_usuario" parentEdge="EAST" positioner="TwoLineUserLinkPositioner">
      <positionableLines>
        <positionableLine lineRole="PARENT_LINE" x1="632" x2="1652" y1="343" y2="343"/>
        <positionableLine lineRole="CHILD_LINE" x1="1656" x2="1656" y1="191" y2="339"/>
      </positionableLines>
    </FkGl>
    <FkGl bkCl="ff000000" childEdge="EAST" nm="public.ciudad.fk_Departamento" parentEdge="WEST" positioner="OneLineUserLinkPositioner">
      <positionableLines>
        <positionableLine lineRole="SINGLE_LINE" x1="724" x2="650" y1="475" y2="475"/>
      </positionableLines>
    </FkGl>
    <FkGl bkCl="ff000000" childEdge="EAST" nm="public.datos_usuario.fk_datos_usuario_Ciudad" parentEdge="WEST" positioner="OneLineUserLinkPositioner">
      <positionableLines>
        <positionableLine lineRole="SINGLE_LINE" x1="359" x2="285" y1="488" y2="488"/>
      </positionableLines>
    </FkGl>
    <FkGl bkCl="ff000000" childEdge="NORTH" nm="public.datos_usuario.fk_datos_usuario_usuario" parentEdge="WEST" positioner="TwoLineUserLinkPositioner">
      <positionableLines>
        <positionableLine lineRole="PARENT_LINE" x1="366" x2="160" y1="343" y2="343"/>
        <positionableLine lineRole="CHILD_LINE" x1="156" x2="156" y1="426" y2="347"/>
      </positionableLines>
    </FkGl>
    <FkGl bkCl="ff000000" childEdge="NORTH" nm="public.detalle_compra_insumo.fk_detalle_compra_insumo_compra_insumo" parentEdge="WEST" positioner="TwoLineUserLinkPositioner">
      <positionableLines>
        <positionableLine lineRole="PARENT_LINE" x1="1800" x2="678" y1="44" y2="44"/>
        <positionableLine lineRole="CHILD_LINE" x1="674" x2="674" y1="621" y2="48"/>
      </positionableLines>
    </FkGl>
    <FkGl bkCl="ff000000" childEdge="" nm="public.detalle_compra_insumo.fk_detalle_compra_insumo_insumo" parentEdge="" positioner="">
      <positionableLines/>
    </FkGl>
    <FkGl bkCl="ff000000" childEdge="WEST" nm="public.detalle_compra_insumo.fk_Insumo" parentEdge="EAST" positioner="OneLineUserLinkPositioner">
      <positionableLines>
        <positionableLine lineRole="SINGLE_LINE" x1="308" x2="537" y1="705" y2="705"/>
      </positionableLines>
    </FkGl>
    <FkGl bkCl="ff000000" childEdge="NORTH" nm="public.entrada_bodega.fk_entrada_bodega_usuario" parentEdge="EAST" positioner="TwoLineUserLinkPositioner">
      <positionableLines>
        <positionableLine lineRole="PARENT_LINE" x1="632" x2="1388" y1="343" y2="343"/>
        <positionableLine lineRole="CHILD_LINE" x1="1392" x2="1392" y1="417" y2="347"/>
      </positionableLines>
    </FkGl>
    <FkGl bkCl="ff000000" childEdge="NORTH" nm="public.gestacion.fk_gestacion_animal" parentEdge="EAST" positioner="TwoLineUserLinkPositioner">
      <positionableLines>
        <positionableLine lineRole="PARENT_LINE" x1="654" x2="1160" y1="115" y2="115"/>
        <positionableLine lineRole="CHILD_LINE" x1="1164" x2="1164" y1="593" y2="119"/>
      </positionableLines>
    </FkGl>
    <FkGl bkCl="ff000000" childEdge="SOUTH" nm="public.gestacion.fk_gestacion_raza" parentEdge="EAST" positioner="TwoLineUserLinkPositioner">
      <positionableLines>
        <positionableLine lineRole="PARENT_LINE" x1="296" x2="1160" y1="837" y2="837"/>
        <positionableLine lineRole="CHILD_LINE" x1="1164" x2="1164" y1="744" y2="833"/>
      </positionableLines>
    </FkGl>
    <FkGl bkCl="ff000000" childEdge="NORTH" nm="public.gestacion.fk_gestacion_usuario" parentEdge="EAST" positioner="TwoLineUserLinkPositioner">
      <positionableLines>
        <positionableLine lineRole="PARENT_LINE" x1="632" x2="1160" y1="343" y2="343"/>
        <positionableLine lineRole="CHILD_LINE" x1="1164" x2="1164" y1="593" y2="347"/>
      </positionableLines>
    </FkGl>
    <FkGl bkCl="ff000000" childEdge="SOUTH" nm="public.insumo.fk_insumo_tipo_insumo" parentEdge="NORTH" positioner="OneLineUserLinkPositioner">
      <positionableLines>
        <positionableLine lineRole="SINGLE_LINE" x1="147" x2="147" y1="904" y2="774"/>
      </positionableLines>
    </FkGl>
    <FkGl bkCl="ff000000" childEdge="SOUTH" nm="public.proceso_venta.fk_proceso_venta_usuario" parentEdge="EAST" positioner="TwoLineUserLinkPositioner">
      <positionableLines>
        <positionableLine lineRole="PARENT_LINE" x1="632" x2="1364" y1="343" y2="343"/>
        <positionableLine lineRole="CHILD_LINE" x1="1368" x2="1368" y1="275" y2="339"/>
      </positionableLines>
    </FkGl>
    <FkGl bkCl="ff000000" childEdge="SOUTH" nm="public.recordar_me.fk_recordar_me_usuario" parentEdge="WEST" positioner="TwoLineUserLinkPositioner">
      <positionableLines>
        <positionableLine lineRole="PARENT_LINE" x1="366" x2="244" y1="314" y2="314"/>
        <positionableLine lineRole="CHILD_LINE" x1="240" x2="240" y1="310" y2="310"/>
      </positionableLines>
    </FkGl>
    <FkGl bkCl="ff000000" childEdge="NORTH" nm="public.registro_parto.fk_registro_parto_animal" parentEdge="SOUTH" positioner="OneLineUserLinkPositioner">
      <positionableLines>
        <positionableLine lineRole="SINGLE_LINE" x1="515" x2="515" y1="204" y2="777"/>
      </positionableLines>
    </FkGl>
    <FkGl bkCl="ff000000" childEdge="WEST" nm="public.registro_parto.fk_registro_parto_raza" parentEdge="EAST" positioner="OneLineUserLinkPositioner">
      <positionableLines>
        <positionableLine lineRole="SINGLE_LINE" x1="296" x2="345" y1="837" y2="837"/>
      </positionableLines>
    </FkGl>
    <FkGl bkCl="ff000000" childEdge="WEST" nm="public.registro_vacunacion.fk_registro_vacunacion_animal" parentEdge="EAST" positioner="OneLineUserLinkPositioner">
      <positionableLines>
        <positionableLine lineRole="SINGLE_LINE" x1="654" x2="721" y1="100" y2="100"/>
      </positionableLines>
    </FkGl>
    <FkGl bkCl="ff000000" childEdge="SOUTH" nm="public.registro_vacunacion.fk_registro_vacunacion_usuario" parentEdge="EAST" positioner="TwoLineUserLinkPositioner">
      <positionableLines>
        <positionableLine lineRole="PARENT_LINE" x1="632" x2="879" y1="343" y2="343"/>
        <positionableLine lineRole="CHILD_LINE" x1="883" x2="883" y1="182" y2="339"/>
      </positionableLines>
    </FkGl>
    <FkGl bkCl="ff000000" childEdge="EAST" nm="public.registro_vacunacion.fk_registro_vacunacion_vacuna" parentEdge="WEST" positioner="OneLineUserLinkPositioner">
      <positionableLines>
        <positionableLine lineRole="SINGLE_LINE" x1="1149" x2="1022" y1="111" y2="111"/>
      </positionableLines>
    </FkGl>
    <FkGl bkCl="ff000000" childEdge="WEST" nm="public.salida_bodega.fk_salida_bodega_usuario" parentEdge="EAST" positioner="OneLineUserLinkPositioner">
      <positionableLines>
        <positionableLine lineRole="SINGLE_LINE" x1="632" x2="1517" y1="375" y2="375"/>
      </positionableLines>
    </FkGl>
    <FkGl bkCl="ff000000" childEdge="EAST" nm="public.usuario_credencial.fk_credencial" parentEdge="WEST" positioner="OneLineUserLinkPositioner">
      <positionableLines>
        <positionableLine lineRole="SINGLE_LINE" x1="1056" x2="982" y1="317" y2="317"/>
      </positionableLines>
    </FkGl>
    <FkGl bkCl="ff000000" childEdge="WEST" nm="public.usuario_credencial.fk_usuario" parentEdge="EAST" positioner="OneLineUserLinkPositioner">
      <positionableLines>
        <positionableLine lineRole="SINGLE_LINE" x1="632" x2="716" y1="317" y2="317"/>
      </positionableLines>
    </FkGl>
    <Notes/>
    <Zones/>
  </Dgm>
  <RnmMgr NxRnmId="7">
    <RnmCh ObjCls="Column" ParCls="Table" ParNme="Genero" SupCls="Schema" SupNme="public">
      <Rnm id="1" nNm="nombre_genero" oNm="nombreGenero"/>
    </RnmCh>
    <RnmCh ObjCls="Column" ParCls="Table" ParNme="registro_parto" SupCls="Schema" SupNme="public">
      <Rnm id="2" nNm="raza_id" oNm="Raza_Id"/>
    </RnmCh>
    <RnmCh ObjCls="Column" ParCls="Table" ParNme="animal" SupCls="Schema" SupNme="public">
      <Rnm id="3" nNm="raza_id" oNm="Raza_Id"/>
    </RnmCh>
    <RnmCh ObjCls="Column" ParCls="Table" ParNme="animal" SupCls="Schema" SupNme="public">
      <Rnm id="4" nNm="lote_id" oNm="Lote_Id"/>
    </RnmCh>
    <RnmCh ObjCls="Table" ParCls="Schema" ParNme="public" SupCls="" SupNme="">
      <Rnm id="5" nNm="vacuna" oNm="Vacuna"/>
    </RnmCh>
    <RnmCh ObjCls="Column" ParCls="Table" ParNme="vacuna" SupCls="Schema" SupNme="public">
      <Rnm id="6" nNm="id" oNm="Id"/>
    </RnmCh>
  </RnmMgr>
  <DbDocOptionMgr>
    <BasicOptionMgr>
      <Name>db.doc.option.mgr</Name>
      <BoolOpt lbl="Diagrams" nm="doc.diagrams" on="1" spl="0"/>
      <BoolOpt lbl="Foreign Keys" nm="doc.fks" on="1" spl="0"/>
      <BoolOpt lbl="Indexes" nm="doc.indexes" on="1" spl="0"/>
      <BoolOpt lbl="Overwrite CSS File" nm="doc.overwrite.css" on="1" spl="0"/>
      <BoolOpt lbl="Procedures" nm="doc.procs" on="1" spl="0"/>
      <BoolOpt lbl="Schemas" nm="doc.schemas" on="1" spl="0"/>
      <BoolOpt lbl="Sequences" nm="doc.sequences" on="1" spl="0"/>
      <BoolOpt lbl="Tables" nm="doc.tables" on="1" spl="0"/>
      <BoolOpt lbl="Triggers" nm="doc.triggers" on="1" spl="0"/>
      <BoolOpt lbl="Views" nm="doc.views" on="1" spl="0"/>
    </BasicOptionMgr>
  </DbDocOptionMgr>
  <OpenEditors>
    <OpenEditor ClsNm="Diagram" fqn="null.diagramA" selected="0"/>
  </OpenEditors>
  <TreePaths>
    <TreePath/>
    <TreePath>/Schemas (2)</TreePath>
    <TreePath>/Schemas (2)/public</TreePath>
    <TreePath>/Schemas (2)/public/Tables (26)</TreePath>
    <TreePath>/Schemas (2)/public/Tables (26)/vacuna</TreePath>
  </TreePaths>
</Db>
